Gemtography/AES.py
Gemtography/__init__.py
Gemtography/test.py
Gemtography-0.0.2.dist-info/LICENSE.md
Gemtography-0.0.2.dist-info/METADATA
Gemtography-0.0.2.dist-info/WHEEL
Gemtography-0.0.2.dist-info/top_level.txt
Gemtography-0.0.2.dist-info/RECORD
